<?xml version="1.0" encoding="UTF-8"?>
<treatment>
  <number>99.</number>
  <genus_name>STYLOCLINE</genus_name>
  <authority>Stylocline Nuttall</authority>
  <place_of_publication>Trans. Amer. Philos. Soc., n. s. 7: 338. 1840</place_of_publication>
  <common_name>Neststraw</common_name>
  <derivation>Greek stylos , column, pillar, or pole, and cline , couch or bed (or gyne , female, specified by Nuttall in protologue), alluding to narrowly cylindric receptacles of the type species</derivation>
  <author_of_tribe_genus>James D. Morefield</author_of_tribe_genus>
  <description>
    <statement id="745.txt-0">
      <text>Annuals , 1–10(–20) cm.</text>
      <structure id="o15676" name="whole_organism">
        <character char_type="range_value" name="atypical_size" from="10" to="20" from_unit="cm" to_unit="cm" from_inclusive="false" />
        <character char_type="range_value" name="size" from="1" from_unit="cm" to="10" to_unit="cm" />
        <character name="life_style" value="annual" />
      </structure>
    </statement>
    <statement id="745.txt-1">
      <text>Stems 1, ± erect, or 2–10+, ascending to ± prostrate.</text>
      <structure id="o15677" name="stem">
        <character name="count" value="1" />
        <character name="orientation" value="erect" modifier="±" />
        <character char_type="range_value" name="count" from="2" to="10" upper_restricted="false" />
        <character name="orientation" value="ascending" />
        <character name="orientation" value="prostrate" modifier="±" />
      </structure>
    </statement>
    <statement id="745.txt-2">
      <text>Leaves cauline;</text>
    </statement>
    <statement id="745.txt-3">
      <text>mostly alternate;</text>
      <structure id="o15678" name="leaf">
        <character name="insertion_or_position" value="cauline" />
        <character name="arrangement" value="alternate" modifier="mostly" />
      </structure>
    </statement>
    <statement id="745.txt-4">
      <text>blades oblanceolate to lanceolate or broader.</text>
      <structure id="o15679" name="blade">
        <character char_type="range_value" name="shape" from="oblanceolate" to="lanceolate" />
        <character name="shape" value="oblanceolate" />
        <character name="shape" value="lanceolate" />
        <character name="size" value="broader" />
      </structure>
    </statement>
    <statement id="745.txt-5">
      <text>Heads in glomerules of 2–10 (rarely borne singly) in ± dichasiform (sometimes ± paniculiform) arrays.</text>
      <structure id="o15680" name="head" />
      <structure id="o15681" name="glomerule" />
      <relation id="r1691" name="in" from="o15680" to="o15681" negation="false" />
      <structure id="o15682" name="array">
        <character char_type="range_value" name="count" from="2" to="10" />
        <character name="arrangement" value="dichasiform" modifier="±" />
      </structure>
      <relation id="r1692" name="consist_of" from="o15681" to="o15682" negation="false" />
    </statement>
    <statement id="745.txt-6">
      <text>Involucres 0 or inconspicuous.</text>
      <structure id="o15683" name="involucre">
        <character name="count" value="0" />
        <character name="manifestation" value="inconspicuous" />
      </structure>
    </statement>
    <statement id="745.txt-7">
      <text>Phyllaries 0, vestigial, or 1–4, unequal or subequal (similar to paleae).</text>
      <structure id="o15684" name="phyllary">
        <character name="count" value="0" />
        <character name="manifestation" value="vestigial" />
        <character char_type="range_value" name="count" from="1" to="4" />
        <character name="size" value="unequal" />
        <character name="size" value="subequal" />
      </structure>
    </statement>
    <statement id="745.txt-8">
      <text>Receptacles cylindric to clavate (heights 2.8–8 times diams.), glabrous.</text>
      <structure id="o15685" name="receptacle">
        <character char_type="range_value" name="shape" from="cylindric" to="clavate" />
        <character name="shape" value="cylindric" />
        <character name="shape" value="clavate" />
        <character name="pubescence" value="glabrous" />
      </structure>
    </statement>
    <statement id="745.txt-9">
      <text>Pistillate paleae falling, erect to ascending;</text>
      <structure id="o15686" name="palea" constraint="pistillate">
        <character char_type="range_value" name="orientation" from="falling , erect" to="ascending" />
        <character name="orientation" value="falling" />
        <character name="orientation" value="erect" />
        <character name="orientation" value="ascending" />
      </structure>
    </statement>
    <statement id="745.txt-10">
      <text>bodies with 5+ nerves (nerves ± parallel, obscure), ± ovate or boat-shaped, saccate most of lengths (obcompressed to terete, not galeate, each usually enclosing a floret, outermost open in 2 spp.);</text>
      <structure id="o15687" name="body">
        <character name="shape" value="ovate" modifier="±" />
        <character name="shape" value="boat-shaped" />
        <character name="architecture_or_shape" value="saccate" constraint="of lengths" constraintid="o15689" />
      </structure>
      <structure id="o15688" name="nerve">
        <character name="count" char_type="range_value" from="5" upper_restricted="false" />
      </structure>
      <relation id="r1693" name="with" from="o15687" to="o15688" negation="false" />
      <structure id="o15689" name="length" />
    </statement>
    <statement id="745.txt-11">
      <text>wings ± erect (apical).</text>
      <structure id="o15690" name="wing">
        <character name="orientation" value="erect" modifier="±" />
      </structure>
    </statement>
    <statement id="745.txt-12">
      <text>Staminate paleae readily falling, mostly 2–4, erect in fruit (not enlarged), shorter than pistillate paleae;</text>
      <structure id="o15691" name="palea" constraint="staminate">
        <character name="orientation" value="falling" modifier="readily" />
        <character char_type="range_value" name="count" from="2" to="4" modifier="mostly" />
        <character name="orientation" value="erect" constraint="in fruit" constraintid="o15692" />
        <character name="size" value="shorter" constraint="than pistillate paleae" constraintid="o15693" />
      </structure>
      <structure id="o15692" name="fruit" />
      <structure id="o15693" name="palea" constraint="pistillate" />
    </statement>
    <statement id="745.txt-13">
      <text>bodies linear-lanceolate to oblanceolate.</text>
      <structure id="o15694" name="body">
        <character char_type="range_value" name="shape" from="linear-lanceolate" to="oblanceolate" />
        <character name="shape" value="linear-lanceolate" />
        <character name="shape" value="oblanceolate" />
      </structure>
    </statement>
    <statement id="745.txt-14">
      <text>Pistillate florets 12–25+.</text>
      <structure id="o15695" name="floret" constraint="pistillate">
        <character char_type="range_value" name="count" from="12" to="25" upper_restricted="false" />
      </structure>
    </statement>
    <statement id="745.txt-15">
      <text>Functionally staminate florets 2–6;</text>
      <structure id="o15696" name="floret" constraint="functionally staminate">
        <character char_type="range_value" name="count" from="2" to="6" />
      </structure>
    </statement>
    <statement id="745.txt-16">
      <text>corolla lobes (4–)5, ± equal.</text>
      <structure id="o15697" name="lobe" constraint="corolla">
        <character char_type="range_value" name="atypical_count" from="4" to="5" to_inclusive="false" />
        <character name="count" value="5" />
        <character name="size" value="equal" modifier="±" />
      </structure>
    </statement>
    <statement id="745.txt-17">
      <text>Bisexual florets 0.</text>
      <structure id="o15698" name="floret" constraint="bisexual">
        <character name="count" value="0" />
      </structure>
    </statement>
    <statement id="745.txt-18">
      <text>Cypselae brown, monomorphic:</text>
    </statement>
    <statement id="745.txt-19">
      <text>compressed to obcompressed, ± obovoid, slightly incurved, abaxially gibbous, faces glabrous, smooth, shiny;</text>
      <structure id="o15699" name="cypsela">
        <character name="coloration" value="brown" />
        <character name="habit" value="monomorphic" />
        <character char_type="range_value" name="shape" from="compressed" to="obcompressed" />
        <character name="shape" value="compressed" />
        <character name="shape" value="obcompressed" />
        <character name="shape" value="obovoid" modifier="±" />
        <character name="orientation" value="incurved" modifier="slightly" />
        <character name="shape" value="gibbous" modifier="abaxially" />
      </structure>
      <structure id="o15700" name="face">
        <character name="pubescence" value="glabrous" />
        <character name="architecture_or_relief" value="smooth" />
        <character name="reflectance" value="shiny" />
      </structure>
    </statement>
    <statement id="745.txt-20">
      <text>corolla scars subapical;</text>
      <structure id="o15701" name="scar" constraint="corolla">
        <character name="insertion_or_position" value="subapical" />
      </structure>
    </statement>
    <statement id="745.txt-21">
      <text>pappi:</text>
      <structure id="o15702" name="pappus" />
    </statement>
    <statement id="745.txt-22">
      <text>pistillate 0, staminate rarely 0, usually of 1–10(–13) bristles (hidden in heads).</text>
      <structure id="o15703" name="pappus" constraint="pistillate">
        <character name="count" value="0" />
      </structure>
      <structure id="o15704" name="pappus" constraint="staminate">
        <character name="count" value="0" modifier="rarely" />
      </structure>
      <structure id="o15705" name="bristle" constraint="-13">
        <character char_type="range_value" name="count" from="1" to="10" />
      </structure>
      <relation id="r1694" name="consist_of" from="o15704" to="o15705" negation="false" modifier="usually" />
    </statement>
    <statement id="745.txt-23">
      <text>x = 14.</text>
      <structure id="o15706" name="chromosome">
        <character name="count" value="14" />
      </structure>
    </statement>
  </description>
  <number_of_infrataxa>Species 7 (7 in the flora):</number_of_infrataxa>
  <general_distribution>sw United States</general_distribution>
  <general_distribution>nw Mexico.</general_distribution>
  <discussion>See discussion of Filagininae following the tribal description (p. 385).</discussion>
  <discussion>Stylocline occurs in Mediterranean, desert, and semi-desert climates; most species appear only after exceptionally wet winters, or in moisture-accumulating microsites (e.g., rock bases, washes, shrub drip-lines). Plants usually grow in undisturbed soils (often with soil crusts) and sometimes colonize stabilized disturbances.</discussion>
  <discussion>In some species of Stylocline, the outermost bracts of heads are merely concave, not saccate; these are paleae (if they subtend and fall with florets) or phyllaries (if they persist and subtend only adjacent saccate paleae). Texture of the palea bodies is diagnostic for each species. In dried specimens, chartaceous bodies tear easily and irregularly when the abaxial indument is gently scraped. Cartilaginous bodies can be scraped clean without tearing and split lengthwise only if forced.</discussion>
  <discussion>Stylocline appears to be ancestral to Micropus and Psilocarphus, and derived from, sister to, and/or reticulate with Logfia (J. D. Morefield 1992). Stylocline citroleum, S. sonorensis, and L. depressa show some transitional traits between the genera.</discussion>
  <references>SELECTED REFERENCE Morefield, J. D. 1992. Evolution and Systematics of Stylocline (Asteraceae: Inuleae). Ph.D. dissertation. Claremont Graduate School. California.</references>
  <key>1.Longest pistillate paleae winged proximally and distally, wings widest in proximal 2/3 of palea lengths; phyllaries ± persistent, elliptic or broader, 1–3.5 mm.</key>
  <key>2.Longest pistillate paleae: wings broadly ovate (bases rounded or cordate); staminate ovaries vestigial, 0–0.2 mm, pappi usually of 1–5 bristles; heads arachnoid to thinly lanuginose (often shiny, indument obscured by palea wings)1. Stylocline gnaphaloides</key>
  <key>2.Longest pistillate paleae: wings elliptic to slightly obovate (bases acute); staminate ovaries partially developed, (0.2–)0.3–0.6 mm, pappi of (5–)6–12(–13) bristles; heads thickly lanuginose (dull, indument evident)2. Stylocline citroleum</key>
  <key>1.Longest pistillate paleae winged distally, wings widest in distal 1/3 of palea lengths; phyllaries 0, vestigial, or falling, ± subulate, mostly 0.1–0.5 mm.</key>
  <key>3.Receptacles clavate, heights 2.8–3.5 times diams.; staminate ovaries partially developed, 0.3–0.6 mm (cypselae 0.6–0.8 mm; heads ± spheric, diams. 3–4 mm; longest pistillate paleae 1.9–3.1 mm; proximal leaves blunt)3. Stylocline sonorensis</key>
  <key>3.Receptacles ± cylindric, heights 4–8 times diams.; staminate ovaries ± vestigial, 0–0.3(–0.4) mm (cypselae 0.8–1.6 mm, heads ovoid to ellipsoid or diams. 5–9 mm, longest pistillate paleae 3.4–4.5 mm and/or proximal leaves acute).</key>
  <key>4.Heads ± spheric, thickly lanuginose, largest diams. 5–9 mm; pistillate paleae: longest 3.4–4.5 mm, outermost saccate.</key>
  <key>5.Bodies of longest pistillate paleae (except midnerves) chartaceous; cypselae compressed; largest capitular leaves (some or all) subulate to lanceolate (widest in proximal 1/3), (7–)11–17 mm (distalmost mainly 1.5–2 times head heights) 4. Stylocline micropoides</key>
  <key>5.Bodies of longest pistillate paleae cartilaginous; cypselae obcompressed; largest capitular leaves (all) ± elliptic to ± oblanceolate (widest in distal 2/3), 4–11 mm (distalmost mainly 0.8–1.2 times head heights)5. Stylocline intertexta</key>
  <key>4.Heads ovoid to ellipsoid, thinly lanuginose, largest diams. 1.5–4 mm; pistillate paleae: longest 2–3.3 mm, outermost open, concave.</key>
  <key>6.Heads 2.5–4 mm diam.; longest pistillate paleae 2.8–3.3 mm; cypselae 1.1–1.6 mm; staminate corollas 1.1–1.7 mm (lobes usually 5); leaves ± acute6. Stylocline psilocarphoides</key>
  <key>6.Heads 1.5–2.5 mm diam.; longest pistillate paleae 2–2.7 mm; cypselae 0.7–1 mm; staminate corollas 0.8–1.1 mm (lobes usually 4); leaves blunt7. Stylocline masonii</key>
</treatment>

<!--produced by $Id: VolumeFinalizer.java 794 2011-04-14 02:35:22Z hong1.cui $
-->